a10_octavia/__init__.py
a10_octavia/a10_config.py
a10_octavia/version.py
a10_octavia/api/__init__.py
a10_octavia/api/drivers/__init__.py
a10_octavia/api/drivers/driver.py
a10_octavia/api/drivers/flavor_schema.py
a10_octavia/cmd/__init__.py
a10_octavia/cmd/a10_health_manager.py
a10_octavia/cmd/a10_house_keeper.py
a10_octavia/cmd/a10_octavia_worker.py
a10_octavia/cmd/driver_agent.py
a10_octavia/cmd/service.py
a10_octavia/cmd/vthunder_heartbeat_udp.py
a10_octavia/common/__init__.py
a10_octavia/common/a10constants.py
a10_octavia/common/config_options.py
a10_octavia/common/config_types.py
a10_octavia/common/data_models.py
a10_octavia/common/defaults.py
a10_octavia/common/exceptions.py
a10_octavia/common/openstack_mappings.py
a10_octavia/common/utils.py
a10_octavia/contrib/README
a10_octavia/contrib/install_contrib_scripts
a10_octavia/contrib/devstack/a10-octavia-devstack-victoria.sh
a10_octavia/contrib/devstack/new-octavia-devstack.sh
a10_octavia/contrib/scripts/a10_adc_tree_create
a10_octavia/contrib/scripts/a10_hard_delete_adc_tree
a10_octavia/contrib/scripts/a10_hard_delete_amphora
a10_octavia/contrib/scripts/a10_services_restart
a10_octavia/contrib/scripts/a10_setup_provider_flat_poc
a10_octavia/contrib/scripts/a10_setup_provider_no_dns
a10_octavia/contrib/scripts/a10_setup_provider_vlan_poc
a10_octavia/contrib/scripts/a10_spawn_lb
a10_octavia/controller/__init__.py
a10_octavia/controller/healthmanager/__init__.py
a10_octavia/controller/healthmanager/a10_health_manager.py
a10_octavia/controller/housekeeping/__init__.py
a10_octavia/controller/housekeeping/house_keeping.py
a10_octavia/controller/queue/__init__.py
a10_octavia/controller/queue/consumer.py
a10_octavia/controller/queue/endpoint.py
a10_octavia/controller/queue/event_queue.py
a10_octavia/controller/worker/__init__.py
a10_octavia/controller/worker/controller_worker.py
a10_octavia/controller/worker/flows/__init__.py
a10_octavia/controller/worker/flows/a10_health_monitor_flows.py
a10_octavia-2.2.0.dist-info/AUTHORS
a10_octavia-2.2.0.dist-info/LICENSE
a10_octavia-2.2.0.dist-info/METADATA
a10_octavia-2.2.0.dist-info/WHEEL
a10_octavia-2.2.0.dist-info/entry_points.txt
a10_octavia-2.2.0.dist-info/pbr.json
a10_octavia-2.2.0.dist-info/top_level.txt
a10_octavia-2.2.0.dist-info/RECORD
