Metadata-Version: 2.1
Name: a10-octavia
Version: 2.2.0
Summary: A10 Octavia Provider Driver
Home-page: https://github.com/a10networks/a10-octavia
Author: A10 Networks
Author-email: opensource@a10networks.com
License: UNKNOWN
Platform: UNKNOWN
Classifier: Development Status :: 2 - Pre-Alpha
Classifier: Environment :: OpenStack
Classifier: Intended Audience :: Developers
Classifier: Intended Audience :: Information Technology
Classifier: Intended Audience :: System Administrators
Classifier: License :: OSI Approved :: Apache Software License
Classifier: Operating System :: POSIX :: Linux
Classifier: Programming Language :: Python
Classifier: Programming Language :: Python :: 2.7
Classifier: Programming Language :: Python :: 3
Classifier: Programming Language :: Python :: 3.5
Requires-Dist: acos-client (>=2.10.0)
Requires-Dist: jsonschema (>=3.2.0)
Requires-Dist: keystone (==18.0.0)
Requires-Dist: octavia-lib
Requires-Dist: octavia (<=10.0.0,>=7.0.0)
Requires-Dist: pyOpenSSL (>=19.1.0)
Requires-Dist: python-barbicanclient (>=4.5.2)
Requires-Dist: python-glanceclient (>=2.8.0)
Requires-Dist: python-novaclient (>=9.1.0)
Requires-Dist: taskflow (>=4.4.0)
Requires-Dist: tenacity (>=5.0.4)
